pkm_buildsys/__init__.py
pkm_buildsys/_vendor/_pyrsistent_version.py
pkm_buildsys/_vendor/attr/__init__.py
pkm_buildsys/_vendor/attr/_compat.py
pkm_buildsys/_vendor/attr/_config.py
pkm_buildsys/_vendor/attr/_funcs.py
pkm_buildsys/_vendor/attr/_make.py
pkm_buildsys/_vendor/attr/_next_gen.py
pkm_buildsys/_vendor/attr/_version_info.py
pkm_buildsys/_vendor/attr/converters.py
pkm_buildsys/_vendor/attr/exceptions.py
pkm_buildsys/_vendor/attr/filters.py
pkm_buildsys/_vendor/attr/py.typed
pkm_buildsys/_vendor/attr/setters.py
pkm_buildsys/_vendor/attr/validators.py
pkm_buildsys/_vendor/attrs.LICENSE
pkm_buildsys/_vendor/jsonschema/COPYING
pkm_buildsys/_vendor/jsonschema/LICENSE
pkm_buildsys/_vendor/jsonschema/__init__.py
pkm_buildsys/_vendor/jsonschema/__main__.py
pkm_buildsys/_vendor/jsonschema/_format.py
pkm_buildsys/_vendor/jsonschema/_legacy_validators.py
pkm_buildsys/_vendor/jsonschema/_reflect.py
pkm_buildsys/_vendor/jsonschema/_types.py
pkm_buildsys/_vendor/jsonschema/_utils.py
pkm_buildsys/_vendor/jsonschema/_validators.py
pkm_buildsys/_vendor/jsonschema/benchmarks/__init__.py
pkm_buildsys/_vendor/jsonschema/benchmarks/issue232.py
pkm_buildsys/_vendor/jsonschema/benchmarks/json_schema_test_suite.py
pkm_buildsys/_vendor/jsonschema/cli.py
pkm_buildsys/_vendor/jsonschema/compat.py
pkm_buildsys/_vendor/jsonschema/exceptions.py
pkm_buildsys/_vendor/jsonschema/schemas/draft3.json
pkm_buildsys/_vendor/jsonschema/schemas/draft4.json
pkm_buildsys/_vendor/jsonschema/schemas/draft6.json
pkm_buildsys/_vendor/jsonschema/schemas/draft7.json
pkm_buildsys/_vendor/jsonschema/validators.py
pkm_buildsys/_vendor/lark/__init__.py
pkm_buildsys/_vendor/lark/__pyinstaller/__init__.py
pkm_buildsys/_vendor/lark/__pyinstaller/hook-lark.py
pkm_buildsys/_vendor/lark/common.py
pkm_buildsys/_vendor/lark/exceptions.py
pkm_buildsys/_vendor/lark/grammar.py
pkm_buildsys/_vendor/lark/grammars/common.lark
pkm_buildsys/_vendor/lark/indenter.py
pkm_buildsys/_vendor/lark/lark.py
pkm_buildsys-0.2.2.dist-info/WHEEL
pkm_buildsys-0.2.2.dist-info/METADATA
pkm_buildsys-0.2.2.dist-info/RECORD
